commoncrawlindex
