Metadata-Version: 1.0
Name: commoncrawlindex
Version: 0.0.6
Summary: Access to an index of Common Crawl URLs.
Home-page: https://github.com/wiseman/common_crawl_index
Author: John Wiseman
Author-email: jjwiseman@gmail.com
License: MIT
Platform: UNKNOWN
Classifier: Intended Audience :: Developers
Classifier: Natural Language :: English
Classifier: Programming Language :: Python
Classifier: Programming Language :: Python :: 2.6
Classifier: Programming Language :: Python :: 2.7
